README.md
setup.py
botarang/__init__.py
botarang/contrib.py
botarang/errors.py
botarang/ui.py
botarang.egg-info/PKG-INFO
botarang.egg-info/SOURCES.txt
botarang.egg-info/dependency_links.txt
botarang.egg-info/requires.txt
botarang.egg-info/top_level.txt
tests/__init__.py
tests/test_compose.py